{"cameraMode":{"drawMode":0,"name":"Shaded","section":"Shading Mode"},"sceneLighting":true,"audioPlay":false,"sceneViewState":{"m_AlwaysRefresh":false,"showFog":true,"showSkybox":true,"showFlares":true,"showImageEffects":true,"showParticleSystems":true,"showVisualEffectGraphs":true,"m_FxEnabled":true},"in2DMode":false,"pivot":{"x":1001.6353149414063,"y":588.1781005859375,"z":-1219.765380859375},"rotation":{"x":-0.01649549975991249,"y":0.10910849273204804,"z":-0.0015069885412231088,"w":0.9941726922988892},"size":0.8660253882408142,"orthographic":false}